ninjapie/__init__.py
ninjapie/__main__.py
ninjapie/env.py
ninjapie/generator.py
ninjapie/path.py
ninjapie/version.py
ninjapie-2.0.3.dist-info/LICENSE
ninjapie-2.0.3.dist-info/METADATA
ninjapie-2.0.3.dist-info/WHEEL
ninjapie-2.0.3.dist-info/entry_points.txt
ninjapie-2.0.3.dist-info/top_level.txt
ninjapie-2.0.3.dist-info/RECORD
