Metadata-Version: 2.1
Name: ninjapie
Version: 2.0.3
Summary: Ninja-based build system with a Python API
Author-email: Nils Asmussen <nils.asmussen@barkhauseninstitut.org>
License: GNU GENERAL PUBLIC LICENSE
Project-URL: Homepage, https://github.com/Barkhausen-Institut/Ninjapie
Keywords: build system,ninja
Classifier: Development Status :: 3 - Alpha
Classifier: Intended Audience :: Developers
Classifier: Topic :: Software Development :: Build Tools
Classifier: License :: OSI Approved :: GNU General Public License v2 (GPLv2)
Classifier: Programming Language :: Python
Classifier: Programming Language :: Python :: 3
Requires-Python: >=3.9
License-File: LICENSE
